[{"id":"0215","name":"ул. 2-я Советская, д. 74, лит. А-Б","address":"ул. 2-я Советская, д. 74, лит. А-Б","cityKey":"tgn","type":"hypermarket","lat":47.230983,"long":38.875137,"opensAt":"0","closesAt":"0","image":null,"is24hStore":true,"hasPetShop":false},{"id":"0046","name":"ул. Большая Бульварная, д. 15","address":"ул. Большая Бульварная, д. 15","cityKey":"tgn","type":"hypermarket","lat":47.245474,"long":38.891592,"opensAt":"9","closesAt":"23","image":null,"is24hStore":false,"hasPetShop":false}]